[
    {
        "description": "ΑΓΓΕΛΙΔΗΣ ΒΑΣΙΛΕΙΟΣ",
        "title": "",
        "url": "",
        "feed": null
    },
    {
        "description": "ΑΝΔΡΕΑΔΑΚΗΣ ΝΙΚΟΛΑΟΣ",
        "title": "",
        "url": "",
        "feed": null
    },
    {
        "description": "ΔΗΜΟΤΣΗΣ ΔΗΜΗΤΡΙΟΣ",
        "title": "",
        "url": "",
        "feed": null
    },
    {
        "description": "ΘΩΜΑ ΑΙΚΑΤΕΡΙΝΗ",
        "title": "",
        "url": "",
        "feed": null
    },
    {
        "description": "ΚΑΜΠΟΥΡΟΠΟΥΛΟΣ ΠΑΝΑΓΙΩΤΗΣ",
        "title": "Καμπουρόπουλος Π.",
        "url": "https://panoskam.github.io/",
        "feed": null
    },
    {
        "description": "ΚΑΡΑΓΙΑΝΝΑΚΗΣ ΒΑΣΙΛΕΙΟΣ",
        "title": "",
        "url": "",
        "feed": null
    },
    {
        "description": "ΚΑΡΥΠΙΔΟΥ ΚΥΡΙΑΚΗ",
        "title": "",
        "url": "",
        "feed": null
    },
    {
        "description": "ΚΟΤΡΩΤΣΙΟΣ ΣΩΤΗΡΙΟΣ",
        "title": "",
        "url": "",
        "feed": null
    },
    {
        "description": "ΜΙΟΓΛΟΥ ΑΛΕΞΑΝΔΡΟΣ",
        "title": "",
        "url": "",
        "feed": null
    },
    {
        "description": "ΝΕΡΑΝΤΖΗΣ ΕΥΑΓΓΕΛΟΣ",
        "title": "",
        "url": "",
        "feed": null
    },
    {
        "description": "ΣΩΠΙΑΔΗΣ ΓΕΩΡΓΙΟΣ",
        "title": "",
        "url": "",
        "feed": null
    },
    {
        "description": "ΤΣΑΓΡΗΣ ΓΡΗΓΟΡΙΟΣ",
        "title": "",
        "url": "",
        "feed": null
    },
    {
        "description": "ΤΣΙΑΝΟΣ ΑΝΤΩΝΙΟΣ",
        "title": "",
        "url": "",
        "feed": null
    },
    {
        "description": "ΦΩΣΚΟΛΟΥ ΑΓΝΗ",
        "title": "",
        "url": "",
        "feed": null
    }
]
